PriorKnowledgeNeuralODE/__init__.py
PriorKnowledgeNeuralODE/adaptiveFuncs.py
PriorKnowledgeNeuralODE_package-1.0.0.dist-info/LICENSE.txt
PriorKnowledgeNeuralODE_package-1.0.0.dist-info/METADATA
PriorKnowledgeNeuralODE_package-1.0.0.dist-info/WHEEL
PriorKnowledgeNeuralODE_package-1.0.0.dist-info/top_level.txt
PriorKnowledgeNeuralODE_package-1.0.0.dist-info/RECORD
