Metadata-Version: 2.1
Name: PriorKnowledgeNeuralODE-package
Version: 1.0.0
Summary: a compilation of methods to incorporate constraints into Neural ODE models
Home-page: https://github.com/CeciliaCoelho/PriorKnowledgeNeuralODE
Author: Cecília Coelho
Author-email: cmartins@cmat.uminho.pt
License: LGPL-2.1
Keywords: Neural ODE,Constrained Optimization,Time-series,Neural Networks
License-File: LICENSE.txt
